setup.py
brynq_toolkit/successfactors/__init__.py
brynq_toolkit/successfactors/get_data.py
brynq_toolkit_successfactors.egg-info/PKG-INFO
brynq_toolkit_successfactors.egg-info/SOURCES.txt
brynq_toolkit_successfactors.egg-info/dependency_links.txt
brynq_toolkit_successfactors.egg-info/not-zip-safe
brynq_toolkit_successfactors.egg-info/requires.txt
brynq_toolkit_successfactors.egg-info/top_level.txt