Metadata-Version: 1.0
Name: brynq-toolkit-successfactors
Version: 0.1.0
Summary: SuccessFactors wrapper from BrynQ
Home-page: UNKNOWN
Author: BrynQ
Author-email: support@brynq.com
License: BrynQ License
Platform: UNKNOWN
